{
    "configurations": [
        {
            "name": "linux-gcc-x64",
            "includePath": [
                "${workspaceFolder}/**",
                "/usr/include/libadwaita-1",
                "/usr/include/gtk-4.0",
                "/usr/include/pango-1.0",
                "/usr/include/glib-2.0",
                "/usr/lib64/glib-2.0/include",
                "/usr/include/harfbuzz",
                "/usr/include/freetype2",
                "/usr/include/libmount",
                "/usr/include/blkid",
                "/usr/include/fribidi",
                "/usr/include/uuid",
                "/usr/include/cairo",
                "/usr/include/pixman-1",
                "/usr/include/libpng16",
                "/usr/include/gdk-pixbuf-2.0",
                "/usr/include/graphene-1.0",
                "/usr/lib64/graphene-1.0/include",
                "/usr/include/gio-unix-2.0",
                "/usr/include/wayland",
                "/usr/include/libxkbcommon"
            ],
            "defines": [],
            "compilerPath": "/usr/bin/gcc",
            "cStandard": "${default}",
            "cppStandard": "${default}",
            "intelliSenseMode": "linux-gcc-x64",
            "compilerArgs": [
                "-Wall",
                "-Wextra",
                "-Wpedantic"
            ],
            "compileCommands": "${workspaceFolder}/builddir/compile_commands.json"
        }
    ],
    "version": 4
}